rtl/controle.v
module controle(instrucao, MemToReg, LeMem, EscMem, ALUOp, Jump, ALUSrc, EscReg1, EscReg2, Halt, DestR2, EscFlag);

input [7:0] instrucao;
output reg ALUOp, Jump, LeMem, EscMem, ALUSrc, EscReg1, EscReg2, Halt, DestR2, EscFlag;
output reg [1:0] MemToReg;

// MemToReg seleciona o dado escrito no banco de registradores (mux_dado em processador.v):
//   00 = resultadoULA   (usado por CMP, embora CMP nao escreva registrador)
//   01 = saidaExtensor  (LOADI)
//   10 = resultadoULA   (INC/DEC)
//   11 = dadoMem        (LOAD)

always @(instrucao) begin
    // Valores padrão
    MemToReg = 2'b00;
    LeMem = 0;
    EscMem = 0;
    ALUOp = 0;
    Jump = 0;
    ALUSrc = 0;
    EscReg1 = 0;
    EscReg2 = 0;
    Halt = 0;
    DestR2 = 0; // por padrao, registrador de escrita = R1
    EscFlag = 0;

    case (instrucao[7:5]) 
        3'b000: begin // STORE: mem[R1] = R2 (endereco em R1, dado em R2)
            EscMem = 1;
        end
        
        3'b001: begin // LOAD: R2 = mem[R1] (endereco em R1, destino em R2)
            LeMem = 1;
            MemToReg = 2'b11;
            EscReg2 = 1;
            DestR2 = 1; // destino da escrita e' R2, nao R1
        end
        
        3'b010: begin // LOADI: R1 = imediato
            MemToReg = 2'b01;
            EscReg2 = 1;
        end
        
        3'b011: begin // JUMP
           Jump = 1;
        end

        3'b100: begin // INC (funct=1) ou DEC (funct=0), destino = R1
            ALUOp = instrucao[0] ? 0 : 1; // 1=INC(soma) -> ALUOp=0 ; 0=DEC(subtracao) -> ALUOp=1
            MemToReg = 2'b10;
            ALUSrc = 1;
            EscReg2 = 1;
        end

        3'b101: begin // CMP: compara R1 com R2 (nao escreve registrador)
           ALUOp = 1;
              EscFlag = 1;
        end

        3'b110: begin // SWAP: troca R1 e R2
           EscReg1 = 1;
           EscReg2 = 1;
        end

        3'b111: begin // HALT
           Halt = 1;
        end

    endcase
end

endmodule

tb/controleTB.v
module controleTB;

// Sinais de teste
reg [7:0] instrucao;
wire [1:0] MemToReg;
wire LeMem, EscMem, ALUOp, Jump, ALUSrc, EscReg1, EscReg2, Halt, DestR2, EscFlag;

// Instância do módulo controle
controle ctrl(instrucao, MemToReg, LeMem, EscMem, ALUOp, Jump, ALUSrc, EscReg1, EscReg2, Halt, DestR2, EscFlag);

task mostra(input [127:0] nome);
begin
    $display("%0s:", nome);
    $display("  MemToReg: %b, LeMem: %b, EscMem: %b, DestR2: %b", MemToReg, LeMem, EscMem, DestR2);
    $display("  ALUOp: %b, Jump: %b, ALUSrc: %b", ALUOp, Jump, ALUSrc);
    $display("  EscReg1: %b, EscReg2: %b, EscFlag: %b, Halt: %b", EscReg1, EscReg2, EscFlag, Halt);
    $display("");
end
endtask

// Geração de formas de onda
initial begin
    $dumpfile("build/vcd/controleTB.vcd");
    $dumpvars(0, controleTB);

    // STORE (000)
    instrucao = 8'b00000000;
    #10; mostra("STORE (000)");

    // LOAD (001)
    instrucao = 8'b00100000;
    #10; mostra("LOAD (001)");

    // LOADI (010)
    instrucao = 8'b01000000;
    #10; mostra("LOADI (010)");

    // JUMP (011)
    instrucao = 8'b01100000;
    #10; mostra("JUMP (011)");

    // DEC (100, funct = 0)
    instrucao = 8'b10000000;
    #10; mostra("DEC (100, funct = 0)");

    // INC (100, funct = 1)
    instrucao = 8'b10000001;
    #10; mostra("INC (100, funct = 1)");

    // CMP (101)
    instrucao = 8'b10100000;
    #10; mostra("CMP (101)");

    // SWAP (110)
    instrucao = 8'b11000000;
    #10; mostra("SWAP (110)");

    // HALT (111)
    instrucao = 8'b11100000;
    #10; mostra("HALT (111)");

    $finish;
end

endmodule

build/vcd/controleTB.vcd
$date
	Sat Aug 15 10:22:39 2026
$end
$version
	Icarus Verilog
$end
$timescale
	1s
$end
$scope module controleTB $end
$var wire 2 ! MemToReg [1:0] $end
$var wire 1 " LeMem $end
$var wire 1 # Jump $end
$var wire 1 $ Halt $end
$var wire 1 % EscReg2 $end
$var wire 1 & EscReg1 $end
$var wire 1 ' EscMem $end
$var wire 1 ( EscFlag $end
$var wire 1 ) DestR2 $end
$var wire 1 * ALUSrc $end
$var wire 1 + ALUOp $end
$var reg 8 , instrucao [7:0] $end
$scope module ctrl $end
$var wire 8 - instrucao [7:0] $end
$var reg 1 + ALUOp $end
$var reg 1 * ALUSrc $end
$var reg 1 ) DestR2 $end
$var reg 1 ( EscFlag $end
$var reg 1 ' EscMem $end
$var reg 1 & EscReg1 $end
$var reg 1 % EscReg2 $end
$var reg 1 $ Halt $end
$var reg 1 # Jump $end
$var reg 1 " LeMem $end
$var reg 2 . MemToReg [1:0] $end
$upscope $end
$scope task mostra $end
$var reg 128 / nome [127:0] $end
$upscope $end
$upscope $end
$enddefinitions $end
$comment Show the parameter values. $end
$dumpall
$end
#0
$dumpvars
bx /
b0 .
b0 -
b0 ,
0+
0*
0)
0(
1'
0&
0%
0$
0#
0"
b0 !
$end
#10
1)
1%
b11 !
b11 .
1"
0'
b100000 ,
b100000 -
b101001101010100010011110101001001000101001000000010100000110000001100000011000000101001 /
#20
0)
1%
0"
b1 !
b1 .
b1000000 ,
b1000000 -
b1001100010011110100000101000100001000000010100000110000001100000011000100101001 /
#30
1#
0%
b0 !
b0 .
b1100000 ,
b1100000 -
b100110001001111010000010100010001001001001000000010100000110000001100010011000000101001 /
#40
1%
1*
b10 !
b10 .
1+
0#
b10000000 ,
b10000000 -
b1001010010101010100110101010000001000000010100000110000001100010011000100101001 /
#50
1%
1*
0+
b10 !
b10 .
b10000001 ,
b10000001 -
b101000001100010011000000110000001011000010000001100110011101010110111001100011011101000010000000111101001000000011000000101001 /
#60
1(
1+
0%
0*
b0 !
b0 .
b10100000 ,
b10100000 -
b101000001100010011000000110000001011000010000001100110011101010110111001100011011101000010000000111101001000000011000100101001 /
#70
1%
1&
0(
0+
b11000000 ,
b11000000 -
b10000110100110101010000001000000010100000110001001100000011000100101001 /
#80
1$
0%
0&
b11100000 ,
b11100000 -
b1010011010101110100000101010000001000000010100000110001001100010011000000101001 /
#90
b1001000010000010100110001010100001000000010100000110001001100010011000100101001 /
