rtl/memDados.v
module memDados(endReg, escMem, leMem, escDado, saiDado, CLOCK);

input CLOCK, escMem, leMem;
input [7:0] endReg, escDado;
output [7:0] saiDado; // combinacional

// Declaração da memória de dados (128 posições de 8 bits)
reg [7:0] mem [0:255];

initial begin
    mem[0] = 8'b00000011;
    mem[1] = 8'b00000001;
    mem[2] = 8'b00000100;
    mem[3] = 8'b00000010;
    // Zera o resto da memória
    for(integer i = 4; i < 256; i++) begin
        mem[i] = 8'b00000000;
    end
end

// Lógica de escrita
always @(posedge CLOCK) begin
    if(escMem) begin
        mem[endReg] <= escDado;
    end 
end

// Leitura combinacional (o dado precisa estar pronto no mesmo ciclo pra chegar no mux de escrita do LOAD)
assign saiDado = mem[endReg];

endmodule

rtl/ULA.v
module ULA(
    input [7:0] r1,      // Entrada R1
    input [7:0] r2,      // Entrada R2
    input ALUOp,         // Sinal de controle (0 para soma, 1 para subtração)
    output reg [7:0] resultado, // Saída de 8 bits do resultado
    output reg lt        // Saida para "set on less than"
);

always @(*) begin

    if (ALUOp == 0) begin
        resultado = r1 + r2;
    end else begin
        resultado = r1 - r2;
    end

    // lt=1 quando r1 > r2 ("maior"); usado pelo JUMP junto com o bit cond (1=maior, 0=menor)
    if (r1 > r2) begin
        lt = 1;
    end else begin
        lt = 0;
    end
end

endmodule

rtl/bancoDeRegs.v
module bancoDeRegs(R1, R2, RegEscrita, dado, escReg1, escReg2, S1, S2, CLOCK);

input CLOCK;
input [7:0] dado;
input escReg1, escReg2;
input [1:0] R1, R2, RegEscrita; // RegEscrita = indice do registrador destino na escrita simples (LOAD usa R2, os demais usam R1)

output reg [7:0] S1, S2; // combinacionais (dependem de R1/R2, nao de clock)

reg [7:0] r0, r1, r2, r3;
reg [7:0] temp1, temp2;

initial begin
    r0 = 8'b0;
    r1 = 8'b0;
    r2 = 8'b0;
    r3 = 8'b0;
    temp1 = 8'b0;
    temp2 = 8'b0;
end

// Borda de subida para escrita
always@(posedge CLOCK) begin
    // Troca de valores entre registradores (SWAP)
    if(escReg1 && escReg2) begin
        // Salva os valores atuais em temporários
        case (R1)
            2'b00: temp1 = r0;
            2'b01: temp1 = r1;
            2'b10: temp1 = r2;
            2'b11: temp1 = r3;
        endcase
        case (R2)
            2'b00: temp2 = r0;
            2'b01: temp2 = r1;
            2'b10: temp2 = r2;
            2'b11: temp2 = r3;
        endcase
        // Realiza a troca usando os temporários
        case (R1)
            2'b00: r0 <= temp2;
            2'b01: r1 <= temp2;
            2'b10: r2 <= temp2;
            2'b11: r3 <= temp2;
        endcase
        case (R2)
            2'b00: r0 <= temp1;
            2'b01: r1 <= temp1;
            2'b10: r2 <= temp1;
            2'b11: r3 <= temp1;
        endcase
    end
    // Escrita padrão: usa RegEscrita (R1 na maioria das instrucoes, R2 no LOAD)
    else if(escReg2) begin
        case (RegEscrita)
            2'b00: begin r0 <= dado; $display("[BancoDeRegs] Escrevendo r0 = %d", dado); end
            2'b01: begin r1 <= dado; $display("[BancoDeRegs] Escrevendo r1 = %d", dado); end
            2'b10: begin r2 <= dado; $display("[BancoDeRegs] Escrevendo r2 = %d", dado); end
            2'b11: begin r3 <= dado; $display("[BancoDeRegs] Escrevendo r3 = %d", dado); end
        endcase
    end
end

// Leitura combinacional (precisa refletir R1/R2 da instrucao atual dentro do mesmo ciclo)
always@(*) begin
    case (R1)
        2'b00: S1 = r0;
        2'b01: S1 = r1;
        2'b10: S1 = r2;
        2'b11: S1 = r3;
    endcase

    case (R2)
        2'b00: S2 = r0;
        2'b01: S2 = r1;
        2'b10: S2 = r2;
        2'b11: S2 = r3;
    endcase
end

endmodule

rtl/controle.v
module controle(instrucao, MemToReg, LeMem, EscMem, ALUOp, Jump, ALUSrc, EscReg1, EscReg2, Halt, DestR2, EscFlag);

input [7:0] instrucao;
output reg ALUOp, Jump, LeMem, EscMem, ALUSrc, EscReg1, EscReg2, Halt, DestR2, EscFlag;
output reg [1:0] MemToReg;

// MemToReg seleciona o dado escrito no banco de registradores (mux_dado em processador.v):
//   00 = resultadoULA   (usado por CMP, embora CMP nao escreva registrador)
//   01 = saidaExtensor  (LOADI)
//   10 = resultadoULA   (INC/DEC)
//   11 = dadoMem        (LOAD)

always @(instrucao) begin
    // Valores padrão
    MemToReg = 2'b00;
    LeMem = 0;
    EscMem = 0;
    ALUOp = 0;
    Jump = 0;
    ALUSrc = 0;
    EscReg1 = 0;
    EscReg2 = 0;
    Halt = 0;
    DestR2 = 0; // por padrao, registrador de escrita = R1
    EscFlag = 0;

    case (instrucao[7:5]) 
        3'b000: begin // STORE: mem[R1] = R2 (endereco em R1, dado em R2)
            EscMem = 1;
        end
        
        3'b001: begin // LOAD: R2 = mem[R1] (endereco em R1, destino em R2)
            LeMem = 1;
            MemToReg = 2'b11;
            EscReg2 = 1;
            DestR2 = 1; // destino da escrita e' R2, nao R1
        end
        
        3'b010: begin // LOADI: R1 = imediato
            MemToReg = 2'b01;
            EscReg2 = 1;
        end
        
        3'b011: begin // JUMP
           Jump = 1;
        end

        3'b100: begin // INC (funct=1) ou DEC (funct=0), destino = R1
            ALUOp = instrucao[0] ? 0 : 1; // 1=INC(soma) -> ALUOp=0 ; 0=DEC(subtracao) -> ALUOp=1
            MemToReg = 2'b10;
            ALUSrc = 1;
            EscReg2 = 1;
        end

        3'b101: begin // CMP: compara R1 com R2 (nao escreve registrador)
           ALUOp = 1;
              EscFlag = 1;
        end

        3'b110: begin // SWAP: troca R1 e R2
           EscReg1 = 1;
           EscReg2 = 1;
        end

        3'b111: begin // HALT
           Halt = 1;
        end

    endcase
end

endmodule

rtl/memInst.v
module memInst(endereco, inst, CLOCK);

input CLOCK;
input [7:0] endereco;
output [7:0] inst;

// Declaração da memória de instruções (256 posições de 8 bits)
reg [7:0] mem [0:255];

initial begin
    for(integer i = 0; i < 256; i++) begin
        mem[i] = 8'b11100000;
    end

    // ================================================================
    // Programa: Bubble Sort (ordem crescente) para mem[0..3]
    // Dados iniciais em memDados.v: [3, 1, 4, 2]
    // Sequencia de comparacoes (bubble sort):
    //   pass 1: (0,1), (1,2), (2,3)
    //   pass 2: (0,1), (1,2)
    //   pass 3: (0,1)
    // ================================================================

    // Inicializa r1 com o endereco de "skip" do bloco 1 (27)
    mem[8]   = 8'b01001111; // LOADI r1, 7
    mem[9]   = 8'b10001111; // INC   r1, 3
    mem[10]  = 8'b10001111; // INC   r1, 3
    mem[11]  = 8'b10001111; // INC   r1, 3
    mem[12]  = 8'b10001111; // INC   r1, 3
    mem[13]  = 8'b10001111; // INC   r1, 3
    mem[14]  = 8'b10001111; // INC   r1, 3
    mem[15]  = 8'b10001101; // INC   r1, 2   -> r1 = 27

    // Bloco 1: compara (0,1)
    mem[16]  = 8'b01000000; // LOADI r0, 0
    mem[17]  = 8'b00100100; // LOAD  [r0] -> r2
    mem[18]  = 8'b01000001; // LOADI r0, 1
    mem[19]  = 8'b00100110; // LOAD  [r0] -> r3
    mem[20]  = 8'b10110110; // CMP   r2, r3
    mem[21]  = 8'b01100001; // JUMP cond=0, r1
    mem[22]  = 8'b11010110; // SWAP  r2, r3
    mem[23]  = 8'b01000000; // LOADI r0, 0
    mem[24]  = 8'b00000100; // STORE [r0] <- r2
    mem[25]  = 8'b01000001; // LOADI r0, 1
    mem[26]  = 8'b00000110; // STORE [r0] <- r3

    // Atualiza r1 para skip do bloco 2 (44)
    mem[27]  = 8'b10001111; // INC   r1, 3
    mem[28]  = 8'b10001111; // INC   r1, 3
    mem[29]  = 8'b10001111; // INC   r1, 3
    mem[30]  = 8'b10001111; // INC   r1, 3
    mem[31]  = 8'b10001111; // INC   r1, 3
    mem[32]  = 8'b10001101; // INC   r1, 2   -> r1 = 44

    // Bloco 2: compara (1,2)
    mem[33]  = 8'b01000001; // LOADI r0, 1
    mem[34]  = 8'b00100100; // LOAD  [r0] -> r2
    mem[35]  = 8'b01000010; // LOADI r0, 2
    mem[36]  = 8'b00100110; // LOAD  [r0] -> r3
    mem[37]  = 8'b10110110; // CMP   r2, r3
    mem[38]  = 8'b01100001; // JUMP cond=0, r1
    mem[39]  = 8'b11010110; // SWAP  r2, r3
    mem[40]  = 8'b01000001; // LOADI r0, 1
    mem[41]  = 8'b00000100; // STORE [r0] <- r2
    mem[42]  = 8'b01000010; // LOADI r0, 2
    mem[43]  = 8'b00000110; // STORE [r0] <- r3

    // Atualiza r1 para skip do bloco 3 (61)
    mem[44]  = 8'b10001111; // INC   r1, 3
    mem[45]  = 8'b10001111; // INC   r1, 3
    mem[46]  = 8'b10001111; // INC   r1, 3
    mem[47]  = 8'b10001111; // INC   r1, 3
    mem[48]  = 8'b10001111; // INC   r1, 3
    mem[49]  = 8'b10001101; // INC   r1, 2   -> r1 = 61

    // Bloco 3: compara (2,3)
    mem[50]  = 8'b01000010; // LOADI r0, 2
    mem[51]  = 8'b00100100; // LOAD  [r0] -> r2
    mem[52]  = 8'b01000011; // LOADI r0, 3
    mem[53]  = 8'b00100110; // LOAD  [r0] -> r3
    mem[54]  = 8'b10110110; // CMP   r2, r3
    mem[55]  = 8'b01100001; // JUMP cond=0, r1
    mem[56]  = 8'b11010110; // SWAP  r2, r3
    mem[57]  = 8'b01000010; // LOADI r0, 2
    mem[58]  = 8'b00000100; // STORE [r0] <- r2
    mem[59]  = 8'b01000011; // LOADI r0, 3
    mem[60]  = 8'b00000110; // STORE [r0] <- r3

    // Atualiza r1 para skip do bloco 4 (78)
    mem[61]  = 8'b10001111; // INC   r1, 3
    mem[62]  = 8'b10001111; // INC   r1, 3
    mem[63]  = 8'b10001111; // INC   r1, 3
    mem[64]  = 8'b10001111; // INC   r1, 3
    mem[65]  = 8'b10001111; // INC   r1, 3
    mem[66]  = 8'b10001101; // INC   r1, 2   -> r1 = 78

    // Bloco 4: compara (0,1)
    mem[67]  = 8'b01000000; // LOADI r0, 0
    mem[68]  = 8'b00100100; // LOAD  [r0] -> r2
    mem[69]  = 8'b01000001; // LOADI r0, 1
    mem[70]  = 8'b00100110; // LOAD  [r0] -> r3
    mem[71]  = 8'b10110110; // CMP   r2, r3
    mem[72]  = 8'b01100001; // JUMP cond=0, r1
    mem[73]  = 8'b11010110; // SWAP  r2, r3
    mem[74]  = 8'b01000000; // LOADI r0, 0
    mem[75]  = 8'b00000100; // STORE [r0] <- r2
    mem[76]  = 8'b01000001; // LOADI r0, 1
    mem[77]  = 8'b00000110; // STORE [r0] <- r3

    // Atualiza r1 para skip do bloco 5 (95)
    mem[78]  = 8'b10001111; // INC   r1, 3
    mem[79]  = 8'b10001111; // INC   r1, 3
    mem[80]  = 8'b10001111; // INC   r1, 3
    mem[81]  = 8'b10001111; // INC   r1, 3
    mem[82]  = 8'b10001111; // INC   r1, 3
    mem[83]  = 8'b10001101; // INC   r1, 2   -> r1 = 95

    // Bloco 5: compara (1,2)
    mem[84]  = 8'b01000001; // LOADI r0, 1
    mem[85]  = 8'b00100100; // LOAD  [r0] -> r2
    mem[86]  = 8'b01000010; // LOADI r0, 2
    mem[87]  = 8'b00100110; // LOAD  [r0] -> r3
    mem[88]  = 8'b10110110; // CMP   r2, r3
    mem[89]  = 8'b01100001; // JUMP cond=0, r1
    mem[90]  = 8'b11010110; // SWAP  r2, r3
    mem[91]  = 8'b01000001; // LOADI r0, 1
    mem[92]  = 8'b00000100; // STORE [r0] <- r2
    mem[93]  = 8'b01000010; // LOADI r0, 2
    mem[94]  = 8'b00000110; // STORE [r0] <- r3

    // Atualiza r1 para skip do bloco 6/fim (112)
    mem[95]  = 8'b10001111; // INC   r1, 3
    mem[96]  = 8'b10001111; // INC   r1, 3
    mem[97]  = 8'b10001111; // INC   r1, 3
    mem[98]  = 8'b10001111; // INC   r1, 3
    mem[99]  = 8'b10001111; // INC   r1, 3
    mem[100] = 8'b10001101; // INC   r1, 2   -> r1 = 112

    // Bloco 6: compara (0,1)
    mem[101] = 8'b01000000; // LOADI r0, 0
    mem[102] = 8'b00100100; // LOAD  [r0] -> r2
    mem[103] = 8'b01000001; // LOADI r0, 1
    mem[104] = 8'b00100110; // LOAD  [r0] -> r3
    mem[105] = 8'b10110110; // CMP   r2, r3
    mem[106] = 8'b01100001; // JUMP cond=0, r1
    mem[107] = 8'b11010110; // SWAP  r2, r3
    mem[108] = 8'b01000000; // LOADI r0, 0
    mem[109] = 8'b00000100; // STORE [r0] <- r2
    mem[110] = 8'b01000001; // LOADI r0, 1
    mem[111] = 8'b00000110; // STORE [r0] <- r3

    // Fim
    mem[112] = 8'b11100000; // HALT
end

// Leitura combinacional (a instrução tem que estar pronta no mesmo ciclo do PC atual)
assign inst = mem[endereco];

endmodule

rtl/PC.v
module PC (HALT, pc, pcNovo, CLOCK);

input HALT;
input CLOCK;
input [7:0] pcNovo;
output reg [7:0] pc;

// Inicialização do PC (Endereço de insturuções começa em 0)
initial begin
    pc = 8'b00001000;
end

always @(posedge CLOCK) begin
    if (!HALT) begin
        pc <= pcNovo;
    end
end

endmodule

rtl/regFlag.v
module regFlag(CLOCK, escFlag, flag, saiFlag);

input CLOCK;
input escFlag;
input flag;
output reg saiFlag;

// Inicialização do registrador
initial begin
    saiFlag = 1'b0;
end

// Lógica do registrador - armazena o flag na borda de subida do clock
always @(posedge CLOCK) begin
    if (escFlag) begin
        saiFlag <= flag;
    end
end

endmodule

rtl/mux.v


module mux(in1, in2, in3, in4, out, sel);

// Mux de 4 entradas pois temos um mux de 3 e dois de 2, então usaremos esse para suprir

input [7:0] in1, in2, in3, in4;
input [1:0] sel;
output reg [7:0] out;

always @(*) begin
    case (sel)
        2'b00: out = in1;
        2'b01: out = in2; 
        2'b10: out = in3;
        2'b11: out = in4;
        default: out = 8'b00000000;
    endcase
end

endmodule

rtl/extensor.v
module extensor(in, out);

input [2:0] in;
output [7:0] out;

// Preenche com zeros os bits mais significativos
assign out = {5'b0, in};

endmodule

rtl/processador.v
module processador(CLOCK);

input CLOCK;

// Sinais internos do processador
wire [7:0] pc, pcNovo, pcMais1, instrucao;
wire [7:0] S1, S2, resultadoULA, saidaExtensor, dadoMem, saidaMux;
wire [1:0] R1, R2, MemToReg, regEscrita;
wire ALUOp, Jump, LeMem, EscMem, ALUSrc, EscReg1, EscReg2, Halt, DestR2, EscFlag;
wire lt, saiFlag;

// Identifica o tipo de instrução (para os muxes de decodificação)
wire isLoadi   = (instrucao[7:5] == 3'b010);
wire isIncDec  = (instrucao[7:5] == 3'b100);
wire isJump    = (instrucao[7:5] == 3'b011);

// Decodificação dos campos de registrador
// Para a maioria das instruções: R1 = instrucao[4:3], R2 = instrucao[2:1]
// Para JUMP: op1 é fixo (00), o registrador-alvo do salto fica em instrucao[1:0]
//            e o bit de condição fica em instrucao[2]
assign R1 = instrucao[4:3];
assign R2 = isJump ? instrucao[1:0] : instrucao[2:1];
wire   condJump = instrucao[2];

// Índice do registrador de escrita: LOAD escreve em R2, as demais em R1
assign regEscrita = DestR2 ? R2 : R1;

// Extensor para LOADI (imediato 3 bits para 8 bits)
extensor extensor_modulo(
    .in(instrucao[2:0]),
    .out(saidaExtensor)
);

// Entrada 1 da ULA
wire [7:0] entradaULA1 = S1;

// Entrada 2 da ULA (S2, ou o imediato correto para LOADI/INC/DEC)
wire [7:0] imediatoIncDec = {6'b0, instrucao[2:1]};
wire [7:0] imediatoLoadi  = {5'b0, instrucao[2:0]};
wire [7:0] entradaULA2 = isLoadi  ? imediatoLoadi :
                         isIncDec ? imediatoIncDec :
                         S2;

// Mux para dado de escrita no banco de registradores
// sel=00 (resultadoULA, não usado p/ escrita atualmente) | sel=01 LOADI | sel=10 INC/DEC | sel=11 LOAD (memória)
mux mux_dado(
    .in1(resultadoULA),
    .in2(saidaExtensor),
    .in3(resultadoULA),
    .in4(dadoMem),
    .out(saidaMux),
    .sel(MemToReg)
);

// Registrador de flag (resultado da última CMP), amostrado na borda de subida
regFlag regFlag_modulo(
    .CLOCK(CLOCK),
    .escFlag(EscFlag),
    .flag(lt),
    .saiFlag(saiFlag)
);

// Cálculo do próximo PC: pc+1, ou o valor do registrador-alvo se o JUMP for tomado
assign pcMais1 = pc + 8'd1;
wire tomaJump = Jump && (saiFlag == condJump);
assign pcNovo = tomaJump ? S2 : pcMais1;

// Instanciação dos módulos principais
PC pc_modulo(.HALT(Halt), .pc(pc), .pcNovo(pcNovo), .CLOCK(CLOCK));

memInst memInst_modulo(.endereco(pc), .inst(instrucao), .CLOCK(CLOCK));

controle controle_modulo(.instrucao(instrucao), .MemToReg(MemToReg), .LeMem(LeMem), 
                       .EscMem(EscMem), .ALUOp(ALUOp), .Jump(Jump), .ALUSrc(ALUSrc), 
                       .EscReg1(EscReg1), .EscReg2(EscReg2), .Halt(Halt), .DestR2(DestR2),
                       .EscFlag(EscFlag));

bancoDeRegs bancoRegs_modulo(
    .R1(R1), .R2(R2), .RegEscrita(regEscrita), .dado(saidaMux), .escReg1(EscReg1),
    .escReg2(EscReg2), .S1(S1), .S2(S2), .CLOCK(CLOCK)
);

ULA ula_modulo(.r1(entradaULA1), .r2(entradaULA2), .ALUOp(ALUOp), 
               .resultado(resultadoULA), .lt(lt));

// Endereço de memória vem de R1 (registrador de endereço), dado a escrever vem de R2
memDados memDados_modulo(.endReg(S1), .escMem(EscMem), .leMem(LeMem), 
                        .escDado(S2), .saiDado(dadoMem), .CLOCK(CLOCK));

endmodule

tb/processadorBubbleSortTB.v
module processadorBubbleSortTB;

    reg CLOCK;
    integer ciclo;

    // Instancia o processador completo
    processador dut(.CLOCK(CLOCK));

    // Clock de 10 unidades de tempo (100 MHz equivalente em escala arbitraria)
    initial begin
        CLOCK = 1'b0;
        forever #5 CLOCK = ~CLOCK;
    end

    task print_header;
    begin
        $display("==============================================================");
        $display("                PROCESSADOR 8 BITS - BUBBLE SORT             ");
        $display("==============================================================");
        $display("Ciclo | PC  | Instrucao | r0  r1  r2  r3 | mem0 mem1 mem2 mem3");
        $display("--------------------------------------------------------------");
    end
    endtask

    task print_state;
    begin
        $display("%5d | %3d | %08b | %2d  %2d  %2d  %2d | %4d %4d %4d %4d",
                 ciclo,
                 dut.pc_modulo.pc,
                 dut.memInst_modulo.mem[dut.pc_modulo.pc],
                 dut.bancoRegs_modulo.r0,
                 dut.bancoRegs_modulo.r1,
                 dut.bancoRegs_modulo.r2,
                 dut.bancoRegs_modulo.r3,
                 dut.memDados_modulo.mem[0],
                 dut.memDados_modulo.mem[1],
                 dut.memDados_modulo.mem[2],
                 dut.memDados_modulo.mem[3]);
    end
    endtask

    task check_result;
    begin
        $display("--------------------------------------------------------------");
        $display("Memoria final: [%0d, %0d, %0d, %0d]",
                 dut.memDados_modulo.mem[0],
                 dut.memDados_modulo.mem[1],
                 dut.memDados_modulo.mem[2],
                 dut.memDados_modulo.mem[3]);

        if (dut.memDados_modulo.mem[0] == 8'd1 &&
            dut.memDados_modulo.mem[1] == 8'd2 &&
            dut.memDados_modulo.mem[2] == 8'd3 &&
            dut.memDados_modulo.mem[3] == 8'd4) begin
            $display("STATUS: PASS - Bubble Sort executado com sucesso.");
        end else begin
            $display("STATUS: FAIL - Vetor nao foi ordenado corretamente.");
        end
        $display("==============================================================");
    end
    endtask

    initial begin
        $dumpfile("build/vcd/processadorBubbleSortTB.vcd");
        $dumpvars(0, processadorBubbleSortTB);

        ciclo = 0;

        print_header();
        print_state();

        // Limite de ciclos para evitar simulacao infinita em caso de erro
        begin : run_loop
            repeat (250) begin
                @(negedge CLOCK);
                ciclo = ciclo + 1;
                print_state();

                if (dut.Halt) begin
                    disable run_loop;
                end
            end
        end

        if (dut.Halt) begin
            $display("HALT detectado no ciclo %0d (PC=%0d).", ciclo, dut.pc_modulo.pc);
        end else begin
            $display("HALT NAO detectado dentro do limite de ciclos.");
        end

        check_result();
        $finish;
    end

endmodule

build/vcd/processadorBubbleSortTB.vcd
$date
	Sat Aug 15 10:19:50 2026
$end
$version
	Icarus Verilog
$end
$timescale
	1s
$end
$scope module processadorBubbleSortTB $end
$var reg 1 ! CLOCK $end
$var integer 32 " ciclo [31:0] $end
$scope module dut $end
$var wire 1 ! CLOCK $end
$var wire 8 # entradaULA1 [7:0] $end
$var wire 1 $ tomaJump $end
$var wire 8 % saidaMux [7:0] $end
$var wire 8 & saidaExtensor [7:0] $end
$var wire 1 ' saiFlag $end
$var wire 8 ( resultadoULA [7:0] $end
$var wire 2 ) regEscrita [1:0] $end
$var wire 8 * pcNovo [7:0] $end
$var wire 8 + pcMais1 [7:0] $end
$var wire 8 , pc [7:0] $end
$var wire 1 - lt $end
$var wire 1 . isLoadi $end
$var wire 1 / isJump $end
$var wire 1 0 isIncDec $end
$var wire 8 1 instrucao [7:0] $end
$var wire 8 2 imediatoLoadi [7:0] $end
$var wire 8 3 imediatoIncDec [7:0] $end
$var wire 8 4 entradaULA2 [7:0] $end
$var wire 8 5 dadoMem [7:0] $end
$var wire 1 6 condJump $end
$var wire 8 7 S2 [7:0] $end
$var wire 8 8 S1 [7:0] $end
$var wire 2 9 R2 [1:0] $end
$var wire 2 : R1 [1:0] $end
$var wire 2 ; MemToReg [1:0] $end
$var wire 1 < LeMem $end
$var wire 1 = Jump $end
$var wire 1 > Halt $end
$var wire 1 ? EscReg2 $end
$var wire 1 @ EscReg1 $end
$var wire 1 A EscMem $end
$var wire 1 B EscFlag $end
$var wire 1 C DestR2 $end
$var wire 1 D ALUSrc $end
$var wire 1 E ALUOp $end
$scope module bancoRegs_modulo $end
$var wire 1 ! CLOCK $end
$var wire 2 F R1 [1:0] $end
$var wire 2 G R2 [1:0] $end
$var wire 2 H RegEscrita [1:0] $end
$var wire 1 ? escReg2 $end
$var wire 1 @ escReg1 $end
$var wire 8 I dado [7:0] $end
$var reg 8 J S1 [7:0] $end
$var reg 8 K S2 [7:0] $end
$var reg 8 L r0 [7:0] $end
$var reg 8 M r1 [7:0] $end
$var reg 8 N r2 [7:0] $end
$var reg 8 O r3 [7:0] $end
$var reg 8 P temp1 [7:0] $end
$var reg 8 Q temp2 [7:0] $end
$upscope $end
$scope module controle_modulo $end
$var wire 8 R instrucao [7:0] $end
$var reg 1 E ALUOp $end
$var reg 1 D ALUSrc $end
$var reg 1 C DestR2 $end
$var reg 1 B EscFlag $end
$var reg 1 A EscMem $end
$var reg 1 @ EscReg1 $end
$var reg 1 ? EscReg2 $end
$var reg 1 > Halt $end
$var reg 1 = Jump $end
$var reg 1 < LeMem $end
$var reg 2 S MemToReg [1:0] $end
$upscope $end
$scope module extensor_modulo $end
$var wire 3 T in [2:0] $end
$var wire 8 U out [7:0] $end
$upscope $end
$scope module memDados_modulo $end
$var wire 1 ! CLOCK $end
$var wire 8 V endReg [7:0] $end
$var wire 8 W escDado [7:0] $end
$var wire 1 A escMem $end
$var wire 1 < leMem $end
$var wire 8 X saiDado [7:0] $end
$scope begin $ivl_for_loop0 $end
$var integer 32 Y i [31:0] $end
$upscope $end
$upscope $end
$scope module memInst_modulo $end
$var wire 1 ! CLOCK $end
$var wire 8 Z inst [7:0] $end
$var wire 8 [ endereco [7:0] $end
$scope begin $ivl_for_loop1 $end
$var integer 32 \ i [31:0] $end
$upscope $end
$upscope $end
$scope module mux_dado $end
$var wire 8 ] in2 [7:0] $end
$var wire 8 ^ in4 [7:0] $end
$var wire 2 _ sel [1:0] $end
$var wire 8 ` in3 [7:0] $end
$var wire 8 a in1 [7:0] $end
$var reg 8 b out [7:0] $end
$upscope $end
$scope module pc_modulo $end
$var wire 1 ! CLOCK $end
$var wire 1 > HALT $end
$var wire 8 c pcNovo [7:0] $end
$var reg 8 d pc [7:0] $end
$upscope $end
$scope module regFlag_modulo $end
$var wire 1 ! CLOCK $end
$var wire 1 B escFlag $end
$var wire 1 - flag $end
$var reg 1 ' saiFlag $end
$upscope $end
$scope module ula_modulo $end
$var wire 1 E ALUOp $end
$var wire 8 e r1 [7:0] $end
$var wire 8 f r2 [7:0] $end
$var reg 1 - lt $end
$var reg 8 g resultado [7:0] $end
$upscope $end
$upscope $end
$scope begin run_loop $end
$upscope $end
$scope task check_result $end
$upscope $end
$scope task print_header $end
$upscope $end
$scope task print_state $end
$upscope $end
$upscope $end
$enddefinitions $end
$comment Show the parameter values. $end
$dumpall
$end
#0
$dumpvars
b111 g
b111 f
b0 e
b1000 d
b1001 c
b111 b
b111 a
b111 `
b1 _
b11 ^
b111 ]
b100000000 \
b1000 [
b1001111 Z
b100000000 Y
b11 X
b0 W
b0 V
b111 U
b111 T
b1 S
b1001111 R
b0 Q
b0 P
b0 O
b0 N
b0 M
b0 L
b0 K
b0 J
b111 I
b1 H
b11 G
b1 F
0E
0D
0C
0B
0A
0@
1?
0>
0=
0<
b1 ;
b1 :
b11 9
b0 8
b0 7
16
b11 5
b111 4
b11 3
b111 2
b1001111 1
00
0/
1.
0-
b1000 ,
b1001 +
b1001 *
b1 )
b111 (
0'
b111 &
b111 %
0$
b0 #
b0 "
0!
$end
#5
1-
b11 4
b11 f
b1010 %
b1010 I
b1010 b
b1010 (
b1010 `
b1010 a
b1010 g
10
0.
1D
1?
b10 ;
b10 S
b10 _
b1010 *
b1010 c
b0 5
b0 X
b0 ^
b111 #
b111 e
b111 8
b111 J
b111 V
b10001111 1
b10001111 R
b10001111 Z
b1010 +
b1001 ,
b1001 [
b1001 d
b111 M
1!
#10
b1 "
0!
#15
b1101 %
b1101 I
b1101 b
b1101 (
b1101 `
b1101 a
b1101 g
b1010 #
b1010 e
b1010 8
b1010 J
b1010 V
b1011 *
b1011 c
b1010 M
b1011 +
b1010 ,
b1010 [
b1010 d
1!
#20
b10 "
0!
#25
b10000 %
b10000 I
b10000 b
b10000 (
b10000 `
b10000 a
b10000 g
b1100 *
b1100 c
b1101 #
b1101 e
b1101 8
b1101 J
b1101 V
b1100 +
b1011 ,
b1011 [
b1011 d
b1101 M
1!
#30
b11 "
0!
#35
b10011 %
b10011 I
b10011 b
b10011 (
b10011 `
b10011 a
b10011 g
b10000 #
b10000 e
b10000 8
b10000 J
b10000 V
b1101 *
b1101 c
b10000 M
b1101 +
b1100 ,
b1100 [
b1100 d
1!
#40
b100 "
0!
#45
b10110 %
b10110 I
b10110 b
b10110 (
b10110 `
b10110 a
b10110 g
b1110 *
b1110 c
b10011 #
b10011 e
b10011 8
b10011 J
b10011 V
b1110 +
b1101 ,
b1101 [
b1101 d
b10011 M
1!
#50
b101 "
0!
#55
b11001 %
b11001 I
b11001 b
b11001 (
b11001 `
b11001 a
b11001 g
b10110 #
b10110 e
b10110 8
b10110 J
b10110 V
b1111 *
b1111 c
b10110 M
b1111 +
b1110 ,
b1110 [
b1110 d
1!
#60
b110 "
0!
#65
b10 4
b10 f
b10 9
b10 G
b11011 %
b11011 I
b11011 b
b11011 (
b11011 `
b11011 a
b11011 g
b101 2
b10 3
b101 &
b101 U
b101 ]
b101 T
1?
1D
b10 ;
b10 S
b10 _
b10000 *
b10000 c
b11001 #
b11001 e
b11001 8
b11001 J
b11001 V
b10001101 1
b10001101 R
b10001101 Z
b10000 +
b1111 ,
b1111 [
b1111 d
b11001 M
1!
#70
b111 "
0!
#75
0-
b0 (
b0 `
b0 a
b0 g
b0 9
b0 G
b0 )
b0 H
b0 4
b0 f
b0 %
b0 I
b0 b
b11 5
b11 X
b11 ^
b0 #
b0 e
b0 8
b0 J
b0 V
b0 2
b0 3
b0 &
b0 U
b0 ]
b0 T
06
b0 :
b0 F
00
1.
1?
0D
b1 ;
b1 S
b1 _
b10001 *
b10001 c
b11011 M
b1000000 1
b1000000 R
b1000000 Z
b10001 +
b10000 ,
b10000 [
b10000 d
1!
#80
b1000 "
0!
#85
b10 )
b10 H
b10 9
b10 G
b11 %
b11 I
b11 b
b100 2
b10 3
b100 &
b100 U
b100 ]
b100 T
16
0.
1C
1<
1?
b11 ;
b11 S
b11 _
b10010 *
b10010 c
b100100 1
b100100 R
b100100 Z
b10010 +
b10001 ,
b10001 [
b10001 d
1!
#90
b1001 "
0!
#95
b1 (
b1 `
b1 a
b1 g
b0 9
b0 G
b1 4
b1 f
b0 )
b0 H
b1 %
b1 I
b1 b
b0 7
b0 K
b0 W
b1 2
b0 3
b1 &
b1 U
b1 ]
b1 T
06
1.
0C
1?
0<
b1 ;
b1 S
b1 _
b10011 *
b10011 c
b11 N
b1000001 1
b1000001 R
b1000001 Z
b10011 +
b10010 ,
b10010 [
b10010 d
1!
#100
b1010 "
0!
#105
1-
b0 4
b0 f
b11 )
b11 H
b11 9
b11 G
b1 (
b1 `
b1 a
b1 g
b110 2
b11 3
b110 &
b110 U
b110 ]
b110 T
16
0.
1C
1<
1?
b11 ;
b11 S
b11 _
b10100 *
b10100 c
b0 7
b0 K
b0 W
b1 5
b1 X
b1 ^
b1 #
b1 e
b1 8
b1 J
b1 V
b100110 1
b100110 R
b100110 Z
b10100 +
b10011 ,
b10011 [
b10011 d
b1 L
1!
#110
b1011 "
0!
#115
b1 4
b1 f
b10 %
b10 I
b10 b
b10 (
b10 `
b10 a
b10 g
b10 )
b10 H
b1 7
b1 K
b1 W
b10 5
b10 X
b10 ^
b11 #
b11 e
b11 8
b11 J
b11 V
b10 :
b10 F
1B
1E
0C
0?
0<
b0 ;
b0 S
b0 _
b10101 *
b10101 c
b1 O
b10110110 1
b10110110 R
b10110110 Z
b10101 +
b10100 ,
b10100 [
b10100 d
1!
#120
b1100 "
0!
